{"metadata": {"dbt_schema_version": "https://schemas.getdbt.com/dbt/run-results/v6.json", "dbt_version": "1.8.7", "generated_at": "2025-05-28T07:06:57.996862Z", "invocation_id": "0ff80567-f2b4-4c95-8b76-322fd3f8d185", "env": {}}, "results": [{"status": "success", "timing": [{"name": "compile", "started_at": "2025-05-28T07:06:14.048895Z", "completed_at": "2025-05-28T07:06:14.056235Z"}, {"name": "execute", "started_at": "2025-05-28T07:06:14.057237Z", "completed_at": "2025-05-28T07:06:57.975602Z"}], "thread_id": "Thread-1 (worker)", "execution_time": 43.92867970466614, "adapter_response": {"_message": "CREATE TABLE (2.4m rows, 367.3 MiB processed)", "code": "CREATE TABLE", "rows_affected": 2425236, "bytes_processed": 385191178, "bytes_billed": 385875968, "location": "US", "project_id": "phonic-sunbeam-461012-g9", "job_id": "c3b97627-3010-4aa2-a849-f2afc351707e", "slot_ms": 5932573}, "message": "CREATE TABLE (2.4m rows, 367.3 MiB processed)", "failures": null, "unique_id": "model.answers.stg_ecommerce__events_microbatch", "compiled": true, "compiled_code": "\n\nWITH source AS (\n\tSELECT *\n\n\tFROM `bigquery-public-data`.`thelook_ecommerce`.`events`\n)\n\nSELECT\n\tid AS event_id,\n\tuser_id,\n\tsequence_number,\n\tsession_id,\n\tcreated_at,\n\tip_address,\n\tcity,\n\tstate,\n\tpostal_code,\n\tbrowser,\n\ttraffic_source,\n\turi AS web_link,\n\tevent_type,\n\t\n\tdbt_choki.get_brand_name(uri) AS brand_name\n\n\nFROM source", "relation_name": "`phonic-sunbeam-461012-g9`.`dbt_choki`.`stg_ecommerce__events_microbatch`"}], "elapsed_time": 48.11724376678467, "args": {"partial_parse": true, "empty": false, "quiet": false, "require_resource_names_without_spaces": false, "show_resource_report": false, "warn_error_options": {"include": [], "exclude": []}, "use_colors_file": true, "indirect_selection": "eager", "write_json": true, "log_file_max_bytes": 10485760, "log_level_file": "debug", "defer": false, "vars": {}, "favor_state": false, "log_level": "info", "static_parser": true, "source_freshness_run_project_hooks": false, "exclude": [], "log_format": "default", "require_explicit_package_overrides_for_builtin_materializations": true, "send_anonymous_usage_stats": true, "which": "run", "macro_debugging": false, "invocation_command": "dbt run -s stg_ecommerce__events_microbatch --profiles-dir .", "log_format_file": "debug", "introspect": true, "cache_selected_only": false, "version_check": true, "strict_mode": false, "printer_width": 80, "project_dir": "C:\\Users\\dchocano\\repos\\dbt-tutorial-course", "profiles_dir": ".", "select": ["stg_ecommerce__events_microbatch"], "populate_cache": true, "partial_parse_file_diff": true, "enable_legacy_logger": false, "use_colors": true, "log_path": "C:\\Users\\dchocano\\repos\\dbt-tutorial-course\\logs", "print": true}}